LICENSE
MANIFEST.in
README.rst
bashtest.py
setup.py
bashtest.egg-info/PKG-INFO
bashtest.egg-info/SOURCES.txt
bashtest.egg-info/dependency_links.txt
bashtest.egg-info/entry_points.txt
bashtest.egg-info/requires.txt
bashtest.egg-info/top_level.txt