Metadata-Version: 2.1
Name: bashtest
Version: 0.0.8
Summary: UNIX command-line tool for bash/shell utils unit testing
Home-page: https://github.com/pahaz/bashtest
Author: Pahaz Blinov
Author-email: pahaz.blinov@gmail.com
License: MIT
Download-URL: https://pypi.python.org/packages/source/s/bashtest/bashtest-0.0.8.zip
Keywords: google spreadsheet api util helper
Platform: unix
Platform: macos
Platform: windows
Classifier: Development Status :: 3 - Alpha
Classifier: Intended Audience :: Developers
Classifier: Topic :: Utilities
Classifier: License :: OSI Approved :: MIT License
Classifier: Programming Language :: Python :: 2
Classifier: Programming Language :: Python :: 2.7
Classifier: Programming Language :: Python :: 3
Classifier: Programming Language :: Python :: 3.4
Classifier: Programming Language :: Python :: 3.5
Provides-Extra: dev
